m4/__init__.py
m4/constant.py
m4/losses/BatchPostivePairLoss.py
m4/losses/__init__.py
m4/models/__init__.py
m4/models/model_base.py
m4/models/BERT/__init__.py
m4/models/BERT/modeling_bert.py
m4/poolers/__init__.py
m4/poolers/poolers.py
m4/targets/__init__.py
m4/targets/pretrain_targets.py
m4/utils/__init__.py
m4/utils/activations.py
m4/utils/args_parser.py
m4/utils/optimization.py
m4/utils/others.py
m4/utils/pretrain.py
m4/utils/similarity.py
m4-0.0.0.dist-info/LICENSE
m4-0.0.0.dist-info/METADATA
m4-0.0.0.dist-info/WHEEL
m4-0.0.0.dist-info/top_level.txt
m4-0.0.0.dist-info/RECORD
