Metadata-Version: 2.1
Name: m4
Version: 0.0.0
Summary: Multilingual, Multimodal, Multitask Models
Home-page: https://github.com/autoliuweijie/m3m
Author: Weijie Liu
Author-email: autoliuweijie@163.com
License: UNKNOWN
Platform: UNKNOWN
Classifier: Programming Language :: Python :: 3
Classifier: License :: OSI Approved :: MIT License
Classifier: Operating System :: OS Independent
Requires-Python: >=3.4
Requires-Dist: torch (>=1.0.0)
Requires-Dist: transformers (>=4.8.1)
